sols/Lin2017.py
sols/__init__.py
LagAquifer3-0.0.1.dist-info/METADATA
LagAquifer3-0.0.1.dist-info/WHEEL
LagAquifer3-0.0.1.dist-info/top_level.txt
LagAquifer3-0.0.1.dist-info/RECORD
