Metadata-Version: 2.1
Name: LagAquifer3
Version: 0.0.1
Summary: The solution developed by Lin and Yeh (2017)
Home-page: UNKNOWN
Author: YF Lin
Author-email: <aar246860@gmail.com>
License: UNKNOWN
Keywords: Aquifer,pumping test,lagging effects
Platform: UNKNOWN
Classifier: Development Status :: 1 - Planning
Classifier: Intended Audience :: Developers
Classifier: Programming Language :: Python :: 3
Classifier: Operating System :: Microsoft :: Windows
